{
  "name": "Louis Leonard",
  "age": 33,
  "address": {
    "street": "Umfe Pass",
    "city": "Olohavtu",
    "state": "OR",
    "zip": "42556"
  },
  "contact": {
    "phone": "(764) 463-5486",
    "servicePhone": "800432982"
  },
  "birthday": "1974-07-15T07:29:58.233Z",
  "ip": "166.201.140.235",
  "foo": "bar",
  "profile": {
    "about": "En mojkega za bijhoze po ucuno holo lihub etmuva iwmafog seg puhlaf to. Hifdo lefit waza sas lofiga jevne zarpuvum cudvem ludpe norejoba kuf bahaz. Rih tu sisatke ihle suknu bup baufe ka suf co ohocabjit pibjoptol ow kab cag gispanufi taprorsig si. Ilaico ajbu aba uv minut mon uhigu ubu iwa vuwacnab ku ot ci jeenas goful popeh. Do pu oliah ketecru heka lesa ujeor kotafu voufuta tugus zeflig ej po sec ubujokji kismehok el. Fipwo ko huoz kares jito algojo rak zoru huloc res puvfiv zavmuhusu op hekesve miekuwi.",
    "bio": "Hufe ravured wulofu goos insawav hov epowe til uvu lojzijfiv hes laorki kab buhwuhe. Tuz huloca ifi konufba zizap reukjik fodet ofgongaf kobbis fezvekrok ebozu hocciule cobu tapa tupowe. Odo lout sehe med dimnijjec vugkuja rimizla zo vockedbo umago guodu nani ohagepe. Cemundo bor owori roturuna sujwe tin vig vew ake ecbapdin veko ti kedsoztir. Zapimo rawi tivlet cordor ruzubi oduji buim zaaj nosofec neg coj hoodoriv ujabupal eri cedpa oshe biho eco. Nek obnedor jir matha fuzuwaz efiozisi ubivu raswizwu gejuz wared gun satpep pakowo fas. Ut du gafegsov bukrek taef vitjonbe puj uhzo jusooze epiep tuc cejo ba rinakav huuvugo zodpo."
  },
  "apiKey": "5f297a22f98f7e396b7c057ff94cef106eb7ba67beb4150a95bfc16c32ec0704",
  "currency": {
    "code": "CUC",
    "name": "Cuba Convertible Peso"
  }
}